es_mcp_client/__init__.py
es_mcp_client/client.py
es_mcp_server/__init__.py
es_mcp_server/client.py
es_mcp_server/config.py
es_mcp_server/server.py
es_mcp_server/tools.py
es_mcp_server-0.1.4.dist-info/METADATA
es_mcp_server-0.1.4.dist-info/WHEEL
es_mcp_server-0.1.4.dist-info/entry_points.txt
es_mcp_server-0.1.4.dist-info/licenses/LICENSE
es_mcp_server-0.1.4.dist-info/RECORD
