Metadata-Version: 2.4
Name: es-mcp-server
Version: 0.1.4
Summary: Elasticsearch MCP 服务器和客户端
Author: Claude-3.7-Sonnet
License-File: LICENSE
Classifier: License :: OSI Approved :: MIT License
Classifier: Operating System :: OS Independent
Classifier: Programming Language :: Python :: 3
Requires-Python: >=3.7
Requires-Dist: aiohttp>=3.8.0
Requires-Dist: elasticsearch7>=7.0.0
Requires-Dist: elasticsearch<9.0,>=8.13
Requires-Dist: mcp>=0.2.0
Requires-Dist: pydantic>=1.8.0
Requires-Dist: python-dotenv>=0.19.0
Provides-Extra: dev
Requires-Dist: pytest-asyncio>=0.19.0; extra == 'dev'
Requires-Dist: pytest>=7.0.0; extra == 'dev'
